LICENSE
README.md
setup.py
./pygpt4all/__init__.py
./pygpt4all/_logger.py
./pygpt4all/constants.py
./pygpt4all/models/__init__.py
./pygpt4all/models/gpt4all.py
./pygpt4all/models/gpt4all_j.py
pygpt4all.egg-info/PKG-INFO
pygpt4all.egg-info/SOURCES.txt
pygpt4all.egg-info/dependency_links.txt
pygpt4all.egg-info/not-zip-safe
pygpt4all.egg-info/requires.txt
pygpt4all.egg-info/top_level.txt