Metadata-Version: 2.1
Name: pygpt4all
Version: 1.0.1
Summary: Official Python CPU inference for GPT4All language models based on llama.cpp and ggml
Author: Abdeladim Sadiki
License: MIT
Requires-Python: >=3.8
License-File: LICENSE
